{
  "_generated_by": "Opradox",
  "_website": "opradox.com",
  "_generated_at": "2025-12-19T09:53:04.921875",
  "data": [
    {
      "Program Kodu": 105710324,
      "Üniversite Türü": "DEVLET",
      "Üniversite Adı": "İZMİR KATİP ÇELEBİ ÜNİVERSİTESİ",
      "Fakülte/Yüksekokul Adı": "Diş Hekimliği Fakültesi",
      "Program Adı": "Diş Hekimliği",
      "Puan Türü": "SAY",
      "Kontenjan": 40,
      "Yerleşen": 40,
      "En Küçük Puan": 47225691,
      "En Büyük Puan": 475.21588,
      "Değer": NaN,
      "AnaProgramAdı": "Diş Hekimliği",
      "DevletAynıSayı": 78,
      "DevletSıra": 16,
      "TÜMsıra": 24,
      "Doluluk Oranı": 100.0
    },
    {
      "Program Kodu": 105710069,
      "Üniversite Türü": "DEVLET",
      "Üniversite Adı": "İZMİR KATİP ÇELEBİ ÜNİVERSİTESİ",
      "Fakülte/Yüksekokul Adı": "Diş Hekimliği Fakültesi",
      "Program Adı": "Diş Hekimliği (İngilizce)",
      "Puan Türü": "SAY",
      "Kontenjan": 40,
      "Yerleşen": 40,
      "En Küçük Puan": 46999137,
      "En Büyük Puan": 475.41577,
      "Değer": NaN,
      "AnaProgramAdı": "Diş Hekimliği",
      "DevletAynıSayı": 78,
      "DevletSıra": 24,
      "TÜMsıra": 38,
      "Doluluk Oranı": 100.0
    },
    {
      "Program Kodu": 105761027,
      "Üniversite Türü": "DEVLET",
      "Üniversite Adı": "İZMİR KATİP ÇELEBİ ÜNİVERSİTESİ",
      "Fakülte/Yüksekokul Adı": "Eczacılık Fakültesi",
      "Program Adı": "Eczacılık",
      "Puan Türü": "SAY",
      "Kontenjan": 45,
      "Yerleşen": 45,
      "En Küçük Puan": 45393797,
      "En Büyük Puan": 459.37466,
      "Değer": NaN,
      "AnaProgramAdı": "Eczacılık",
      "DevletAynıSayı": 36,
      "DevletSıra": 10,
      "TÜMsıra": 16,
      "Doluluk Oranı": 100.0
    },
    {
      "Program Kodu": 105761151,
      "Üniversite Türü": "DEVLET",
      "Üniversite Adı": "İZMİR KATİP ÇELEBİ ÜNİVERSİTESİ",
      "Fakülte/Yüksekokul Adı": "Gemi İnşaatı ve Denizcilik Fakültesi",
      "Program Adı": "Gemi İnşaatı ve Gemi Makineleri Mühendisliği",
      "Puan Türü": "SAY",
      "Kontenjan": 30,
      "Yerleşen": 30,
      "En Küçük Puan": 42341073,
      "En Büyük Puan": 444.08821,
      "Değer": NaN,
      "AnaProgramAdı": "Gemi İnşaatı ve Gemi Makineleri Mühendisliği",
      "DevletAynıSayı": 12,
      "DevletSıra": 4,
      "TÜMsıra": 4,
      "Doluluk Oranı": 100.0
    },
    {
      "Program Kodu": 105761221,
      "Üniversite Türü": "DEVLET",
      "Üniversite Adı": "İZMİR KATİP ÇELEBİ ÜNİVERSİTESİ",
      "Fakülte/Yüksekokul Adı": "Gemi İnşaatı ve Denizcilik Fakültesi",
      "Program Adı": "Gemi ve Deniz Teknolojisi Mühendisliği",
      "Puan Türü": "SAY",
      "Kontenjan": 20,
      "Yerleşen": 20,
      "En Küçük Puan": 4000415,
      "En Büyük Puan": 420.21639,
      "Değer": NaN,
      "AnaProgramAdı": "Gemi ve Deniz Teknolojisi Mühendisliği",
      "DevletAynıSayı": 2,
      "DevletSıra": 2,
      "TÜMsıra": 2,
      "Doluluk Oranı": 100.0
    },
    {
      "Program Kodu": 105761158,
      "Üniversite Türü": "DEVLET",
      "Üniversite Adı": "İZMİR KATİP ÇELEBİ ÜNİVERSİTESİ",
      "Fakülte/Yüksekokul Adı": "Hukuk Fakültesi",
      "Program Adı": "Hukuk",
      "Puan Türü": "EA",
      "Kontenjan": 60,
      "Yerleşen": 60,
      "En Küçük Puan": 41697723,
      "En Büyük Puan": 452.93725,
      "Değer": NaN,
      "AnaProgramAdı": "Hukuk",
      "DevletAynıSayı": 53,
      "DevletSıra": 17,
      "TÜMsıra": 38,
      "Doluluk Oranı": 100.0
    },
    {
      "Program Kodu": 105761029,
      "Üniversite Türü": "DEVLET",
      "Üniversite Adı": "İZMİR KATİP ÇELEBİ ÜNİVERSİTESİ",
      "Fakülte/Yüksekokul Adı": "İktisadi ve İdari Bilimler Fakültesi",
      "Program Adı": "İktisat (İngilizce)",
      "Puan Türü": "EA",
      "Kontenjan": 60,
      "Yerleşen": 62,
      "En Küçük Puan": 33691444,
      "En Büyük Puan": 364.89807,
      "Değer": NaN,
      "AnaProgramAdı": "İktisat",
      "DevletAynıSayı": 131,
      "DevletSıra": 25,
      "TÜMsıra": 42,
      "Doluluk Oranı": 103.33333333333334
    },
    {
      "Program Kodu": 105710121,
      "Üniversite Türü": "DEVLET",
      "Üniversite Adı": "İZMİR KATİP ÇELEBİ ÜNİVERSİTESİ",
      "Fakülte/Yüksekokul Adı": "İktisadi ve İdari Bilimler Fakültesi",
      "Program Adı": "İşletme",
      "Puan Türü": "EA",
      "Kontenjan": 40,
      "Yerleşen": 40,
      "En Küçük Puan": 33337874,
      "En Büyük Puan": 362.75271,
      "Değer": NaN,
      "AnaProgramAdı": "İşletme",
      "DevletAynıSayı": 150,
      "DevletSıra": 39,
      "TÜMsıra": 91,
      "Doluluk Oranı": 100.0
    },
    {
      "Program Kodu": 105761134,
      "Üniversite Türü": "DEVLET",
      "Üniversite Adı": "İZMİR KATİP ÇELEBİ ÜNİVERSİTESİ",
      "Fakülte/Yüksekokul Adı": "İktisadi ve İdari Bilimler Fakültesi",
      "Program Adı": "Maliye",
      "Puan Türü": "EA",
      "Kontenjan": 60,
      "Yerleşen": 60,
      "En Küçük Puan": 31592201,
      "En Büyük Puan": 330.92711,
      "Değer": NaN,
      "AnaProgramAdı": "Maliye",
      "DevletAynıSayı": 60,
      "DevletSıra": 14,
      "TÜMsıra": 15,
      "Doluluk Oranı": 100.0
    },
    {
      "Program Kodu": 105761135,
      "Üniversite Türü": "DEVLET",
      "Üniversite Adı": "İZMİR KATİP ÇELEBİ ÜNİVERSİTESİ",
      "Fakülte/Yüksekokul Adı": "İktisadi ve İdari Bilimler Fakültesi",
      "Program Adı": "Sağlık Yönetimi",
      "Puan Türü": "EA",
      "Kontenjan": 50,
      "Yerleşen": 51,
      "En Küçük Puan": 30271141,
      "En Büyük Puan": 336.89028,
      "Değer": NaN,
      "AnaProgramAdı": "Sağlık Yönetimi",
      "DevletAynıSayı": 64,
      "DevletSıra": 14,
      "TÜMsıra": 32,
      "Doluluk Oranı": 102.0
    },
    {
      "Program Kodu": 105710342,
      "Üniversite Türü": "DEVLET",
      "Üniversite Adı": "İZMİR KATİP ÇELEBİ ÜNİVERSİTESİ",
      "Fakülte/Yüksekokul Adı": "İktisadi ve İdari Bilimler Fakültesi",
      "Program Adı": "Siyaset Bilimi ve Kamu Yönetimi (İngilizce)",
      "Puan Türü": "EA",
      "Kontenjan": 60,
      "Yerleşen": 62,
      "En Küçük Puan": 3182564,
      "En Büyük Puan": 342.91274,
      "Değer": NaN,
      "AnaProgramAdı": "Siyaset Bilimi ve Kamu Yönetimi",
      "DevletAynıSayı": 90,
      "DevletSıra": 79,
      "TÜMsıra": 127,
      "Doluluk Oranı": 103.33333333333334
    },
    {
      "Program Kodu": 105761228,
      "Üniversite Türü": "DEVLET",
      "Üniversite Adı": "İZMİR KATİP ÇELEBİ ÜNİVERSİTESİ",
      "Fakülte/Yüksekokul Adı": "İktisadi ve İdari Bilimler Fakültesi",
      "Program Adı": "Uluslararası İlişkiler (İngilizce)",
      "Puan Türü": "EA",
      "Kontenjan": 55,
      "Yerleşen": 57,
      "En Küçük Puan": 33810463,
      "En Büyük Puan": 361.90741,
      "Değer": NaN,
      "AnaProgramAdı": "Uluslararası İlişkiler",
      "DevletAynıSayı": 64,
      "DevletSıra": 16,
      "TÜMsıra": 24,
      "Doluluk Oranı": 103.63636363636364
    },
    {
      "Program Kodu": 105761092,
      "Üniversite Türü": "DEVLET",
      "Üniversite Adı": "İZMİR KATİP ÇELEBİ ÜNİVERSİTESİ",
      "Fakülte/Yüksekokul Adı": "İktisadi ve İdari Bilimler Fakültesi",
      "Program Adı": "Uluslararası Ticaret ve İşletmecilik (İngilizce)",
      "Puan Türü": "EA",
      "Kontenjan": 60,
      "Yerleşen": 60,
      "En Küçük Puan": 34762241,
      "En Büyük Puan": 380.03593,
      "Değer": NaN,
      "AnaProgramAdı": "Uluslararası Ticaret ve İşletmecilik",
      "DevletAynıSayı": 18,
      "DevletSıra": 2,
      "TÜMsıra": 8,
      "Doluluk Oranı": 100.0
    },
    {
      "Program Kodu": 105761256,
      "Üniversite Türü": "DEVLET",
      "Üniversite Adı": "İZMİR KATİP ÇELEBİ ÜNİVERSİTESİ",
      "Fakülte/Yüksekokul Adı": "İktisadi ve İdari Bilimler Fakültesi",
      "Program Adı": "Veri Bilimi ve Analitiği (İngilizce)",
      "Puan Türü": "SAY",
      "Kontenjan": 30,
      "Yerleşen": 30,
      "En Küçük Puan": 37130556,
      "En Büyük Puan": 436.45676,
      "Değer": NaN,
      "AnaProgramAdı": "Veri Bilimi ve Analitiği",
      "DevletAynıSayı": 17,
      "DevletSıra": 5,
      "TÜMsıra": 6,
      "Doluluk Oranı": 100.0
    },
    {
      "Program Kodu": 105761263,
      "Üniversite Türü": "DEVLET",
      "Üniversite Adı": "İZMİR KATİP ÇELEBİ ÜNİVERSİTESİ",
      "Fakülte/Yüksekokul Adı": "İktisadi ve İdari Bilimler Fakültesi",
      "Program Adı": "Veri Bilimi ve Analitiği (İngilizce) (KKTC Uyruklu)",
      "Puan Türü": "SAY",
      "Kontenjan": 1,
      "Yerleşen": 1,
      "En Küçük Puan": 23484004,
      "En Büyük Puan": 234.84004,
      "Değer": NaN,
      "AnaProgramAdı": "Veri Bilimi ve Analitiği",
      "DevletAynıSayı": 17,
      "DevletSıra": 11,
      "TÜMsıra": 19,
      "Doluluk Oranı": 100.0
    },
    {
      "Program Kodu": 105761165,
      "Üniversite Türü": "DEVLET",
      "Üniversite Adı": "İZMİR KATİP ÇELEBİ ÜNİVERSİTESİ",
      "Fakülte/Yüksekokul Adı": "İlahiyat Fakültesi",
      "Program Adı": "İlahiyat",
      "Puan Türü": "SÖZ",
      "Kontenjan": 99,
      "Yerleşen": 101,
      "En Küçük Puan": 2787204,
      "En Büyük Puan": 370.28931,
      "Değer": NaN,
      "AnaProgramAdı": "İlahiyat",
      "DevletAynıSayı": 197,
      "DevletSıra": 181,
      "TÜMsıra": 186,
      "Doluluk Oranı": 102.020202020202
    },
    {
      "Program Kodu": 105761270,
      "Üniversite Türü": "DEVLET",
      "Üniversite Adı": "İZMİR KATİP ÇELEBİ ÜNİVERSİTESİ",
      "Fakülte/Yüksekokul Adı": "İlahiyat Fakültesi",
      "Program Adı": "İlahiyat (KKTC Uyruklu)",
      "Puan Türü": "SÖZ",
      "Kontenjan": 2,
      "Yerleşen": 0,
      "En Küçük Puan": 0,
      "En Büyük Puan": 0.0,
      "Değer": NaN,
      "AnaProgramAdı": "İlahiyat",
      "DevletAynıSayı": 197,
      "DevletSıra": 189,
      "TÜMsıra": 194,
      "Doluluk Oranı": 0.0
    },
    {
      "Program Kodu": 105761172,
      "Üniversite Türü": "DEVLET",
      "Üniversite Adı": "İZMİR KATİP ÇELEBİ ÜNİVERSİTESİ",
      "Fakülte/Yüksekokul Adı": "İlahiyat Fakültesi",
      "Program Adı": "İlahiyat (M.T.O.K.)",
      "Puan Türü": "SÖZ",
      "Kontenjan": 11,
      "Yerleşen": 11,
      "En Küçük Puan": 26353322,
      "En Büyük Puan": 285.18964,
      "Değer": NaN,
      "AnaProgramAdı": "İlahiyat",
      "DevletAynıSayı": 197,
      "DevletSıra": 93,
      "TÜMsıra": 95,
      "Doluluk Oranı": 100.0
    },
    {
      "Program Kodu": 105761137,
      "Üniversite Türü": "DEVLET",
      "Üniversite Adı": "İZMİR KATİP ÇELEBİ ÜNİVERSİTESİ",
      "Fakülte/Yüksekokul Adı": "Mühendislik ve Mimarlık Fakültesi",
      "Program Adı": "Bilgisayar Mühendisliği (İngilizce)",
      "Puan Türü": "SAY",
      "Kontenjan": 80,
      "Yerleşen": 80,
      "En Küçük Puan": 4384526,
      "En Büyük Puan": 459.03188,
      "Değer": NaN,
      "AnaProgramAdı": "Bilgisayar Mühendisliği",
      "DevletAynıSayı": 140,
      "DevletSıra": 123,
      "TÜMsıra": 282,
      "Doluluk Oranı": 100.0
    },
    {
      "Program Kodu": 105710103,
      "Üniversite Türü": "DEVLET",
      "Üniversite Adı": "İZMİR KATİP ÇELEBİ ÜNİVERSİTESİ",
      "Fakülte/Yüksekokul Adı": "Mühendislik ve Mimarlık Fakültesi",
      "Program Adı": "Biyomedikal Mühendisliği (İngilizce)",
      "Puan Türü": "SAY",
      "Kontenjan": 50,
      "Yerleşen": 51,
      "En Küçük Puan": 36347705,
      "En Büyük Puan": 414.36031,
      "Değer": NaN,
      "AnaProgramAdı": "Biyomedikal Mühendisliği",
      "DevletAynıSayı": 22,
      "DevletSıra": 3,
      "TÜMsıra": 15,
      "Doluluk Oranı": 102.0
    },
    {
      "Program Kodu": 105710042,
      "Üniversite Türü": "DEVLET",
      "Üniversite Adı": "İZMİR KATİP ÇELEBİ ÜNİVERSİTESİ",
      "Fakülte/Yüksekokul Adı": "Mühendislik ve Mimarlık Fakültesi",
      "Program Adı": "Elektrik-Elektronik Mühendisliği (İngilizce)",
      "Puan Türü": "SAY",
      "Kontenjan": 50,
      "Yerleşen": 50,
      "En Küçük Puan": 43446068,
      "En Büyük Puan": 451.67105,
      "Değer": NaN,
      "AnaProgramAdı": "Elektrik-Elektronik Mühendisliği",
      "DevletAynıSayı": 119,
      "DevletSıra": 19,
      "TÜMsıra": 42,
      "Doluluk Oranı": 100.0
    },
    {
      "Program Kodu": 105710184,
      "Üniversite Türü": "DEVLET",
      "Üniversite Adı": "İZMİR KATİP ÇELEBİ ÜNİVERSİTESİ",
      "Fakülte/Yüksekokul Adı": "Mühendislik ve Mimarlık Fakültesi",
      "Program Adı": "Harita Mühendisliği (İngilizce)",
      "Puan Türü": "SAY",
      "Kontenjan": 60,
      "Yerleşen": 62,
      "En Küçük Puan": 30500914,
      "En Büyük Puan": 374.38464,
      "Değer": NaN,
      "AnaProgramAdı": "Harita Mühendisliği",
      "DevletAynıSayı": 22,
      "DevletSıra": 11,
      "TÜMsıra": 12,
      "Doluluk Oranı": 103.33333333333334
    },
    {
      "Program Kodu": 105761179,
      "Üniversite Türü": "DEVLET",
      "Üniversite Adı": "İZMİR KATİP ÇELEBİ ÜNİVERSİTESİ",
      "Fakülte/Yüksekokul Adı": "Mühendislik ve Mimarlık Fakültesi",
      "Program Adı": "Harita Mühendisliği (İngilizce) (KKTC Uyruklu)",
      "Puan Türü": "SAY",
      "Kontenjan": 2,
      "Yerleşen": 0,
      "En Küçük Puan": 0,
      "En Büyük Puan": 0.0,
      "Değer": NaN,
      "AnaProgramAdı": "Harita Mühendisliği",
      "DevletAynıSayı": 22,
      "DevletSıra": 18,
      "TÜMsıra": 19,
      "Doluluk Oranı": 0.0
    },
    {
      "Program Kodu": 105710087,
      "Üniversite Türü": "DEVLET",
      "Üniversite Adı": "İZMİR KATİP ÇELEBİ ÜNİVERSİTESİ",
      "Fakülte/Yüksekokul Adı": "Mühendislik ve Mimarlık Fakültesi",
      "Program Adı": "İnşaat Mühendisliği (İngilizce)",
      "Puan Türü": "SAY",
      "Kontenjan": 30,
      "Yerleşen": 30,
      "En Küçük Puan": 36696485,
      "En Büyük Puan": 399.88792,
      "Değer": NaN,
      "AnaProgramAdı": "İnşaat Mühendisliği",
      "DevletAynıSayı": 113,
      "DevletSıra": 24,
      "TÜMsıra": 40,
      "Doluluk Oranı": 100.0
    },
    {
      "Program Kodu": 105710051,
      "Üniversite Türü": "DEVLET",
      "Üniversite Adı": "İZMİR KATİP ÇELEBİ ÜNİVERSİTESİ",
      "Fakülte/Yüksekokul Adı": "Mühendislik ve Mimarlık Fakültesi",
      "Program Adı": "Makine Mühendisliği (İngilizce)",
      "Puan Türü": "SAY",
      "Kontenjan": 60,
      "Yerleşen": 60,
      "En Küçük Puan": 41692417,
      "En Büyük Puan": 445.57404,
      "Değer": NaN,
      "AnaProgramAdı": "Makine Mühendisliği",
      "DevletAynıSayı": 118,
      "DevletSıra": 24,
      "TÜMsıra": 48,
      "Doluluk Oranı": 100.0
    },
    {
      "Program Kodu": 105710112,
      "Üniversite Türü": "DEVLET",
      "Üniversite Adı": "İZMİR KATİP ÇELEBİ ÜNİVERSİTESİ",
      "Fakülte/Yüksekokul Adı": "Mühendislik ve Mimarlık Fakültesi",
      "Program Adı": "Mekatronik Mühendisliği (İngilizce)",
      "Puan Türü": "SAY",
      "Kontenjan": 75,
      "Yerleşen": 75,
      "En Küçük Puan": 39564164,
      "En Büyük Puan": 433.83452,
      "Değer": NaN,
      "AnaProgramAdı": "Mekatronik Mühendisliği",
      "DevletAynıSayı": 31,
      "DevletSıra": 5,
      "TÜMsıra": 13,
      "Doluluk Oranı": 100.0
    },
    {
      "Program Kodu": 105761144,
      "Üniversite Türü": "DEVLET",
      "Üniversite Adı": "İZMİR KATİP ÇELEBİ ÜNİVERSİTESİ",
      "Fakülte/Yüksekokul Adı": "Mühendislik ve Mimarlık Fakültesi",
      "Program Adı": "Metalurji ve Malzeme Mühendisliği (İngilizce)",
      "Puan Türü": "SAY",
      "Kontenjan": 75,
      "Yerleşen": 77,
      "En Küçük Puan": 36291221,
      "En Büyük Puan": 390.14104,
      "Değer": NaN,
      "AnaProgramAdı": "Metalurji ve Malzeme Mühendisliği",
      "DevletAynıSayı": 45,
      "DevletSıra": 17,
      "TÜMsıra": 18,
      "Doluluk Oranı": 102.66666666666666
    },
    {
      "Program Kodu": 105710315,
      "Üniversite Türü": "DEVLET",
      "Üniversite Adı": "İZMİR KATİP ÇELEBİ ÜNİVERSİTESİ",
      "Fakülte/Yüksekokul Adı": "Mühendislik ve Mimarlık Fakültesi",
      "Program Adı": "Petrol ve Doğalgaz Mühendisliği (İngilizce)",
      "Puan Türü": "SAY",
      "Kontenjan": 35,
      "Yerleşen": 35,
      "En Küçük Puan": 35998724,
      "En Büyük Puan": 396.21818,
      "Değer": NaN,
      "AnaProgramAdı": "Petrol ve Doğalgaz Mühendisliği",
      "DevletAynıSayı": 7,
      "DevletSıra": 3,
      "TÜMsıra": 3,
      "Doluluk Oranı": 100.0
    },
    {
      "Program Kodu": 105761032,
      "Üniversite Türü": "DEVLET",
      "Üniversite Adı": "İZMİR KATİP ÇELEBİ ÜNİVERSİTESİ",
      "Fakülte/Yüksekokul Adı": "Orman Fakültesi",
      "Program Adı": "Orman Endüstrisi Mühendisliği",
      "Puan Türü": "SAY",
      "Kontenjan": 30,
      "Yerleşen": 30,
      "En Küçük Puan": 28806192,
      "En Büyük Puan": 304.33101,
      "Değer": NaN,
      "AnaProgramAdı": "Orman Endüstrisi Mühendisliği",
      "DevletAynıSayı": 10,
      "DevletSıra": 2,
      "TÜMsıra": 2,
      "Doluluk Oranı": 100.0
    },
    {
      "Program Kodu": 105761090,
      "Üniversite Türü": "DEVLET",
      "Üniversite Adı": "İZMİR KATİP ÇELEBİ ÜNİVERSİTESİ",
      "Fakülte/Yüksekokul Adı": "Orman Fakültesi",
      "Program Adı": "Orman Mühendisliği",
      "Puan Türü": "SAY",
      "Kontenjan": 30,
      "Yerleşen": 30,
      "En Küçük Puan": 30931744,
      "En Büyük Puan": 373.8291,
      "Değer": NaN,
      "AnaProgramAdı": "Orman Mühendisliği",
      "DevletAynıSayı": 13,
      "DevletSıra": 1,
      "TÜMsıra": 1,
      "Doluluk Oranı": 100.0
    },
    {
      "Program Kodu": 105710281,
      "Üniversite Türü": "DEVLET",
      "Üniversite Adı": "İZMİR KATİP ÇELEBİ ÜNİVERSİTESİ",
      "Fakülte/Yüksekokul Adı": "Sağlık Bilimleri Fakültesi",
      "Program Adı": "Beslenme ve Diyetetik",
      "Puan Türü": "SAY",
      "Kontenjan": 27,
      "Yerleşen": 27,
      "En Küçük Puan": 34475041,
      "En Büyük Puan": 375.86967,
      "Değer": NaN,
      "AnaProgramAdı": "Beslenme ve Diyetetik",
      "DevletAynıSayı": 66,
      "DevletSıra": 11,
      "TÜMsıra": 27,
      "Doluluk Oranı": 100.0
    },
    {
      "Program Kodu": 105710333,
      "Üniversite Türü": "DEVLET",
      "Üniversite Adı": "İZMİR KATİP ÇELEBİ ÜNİVERSİTESİ",
      "Fakülte/Yüksekokul Adı": "Sağlık Bilimleri Fakültesi",
      "Program Adı": "Fizyoterapi ve Rehabilitasyon",
      "Puan Türü": "SAY",
      "Kontenjan": 60,
      "Yerleşen": 60,
      "En Küçük Puan": 33620583,
      "En Büyük Puan": 396.74444,
      "Değer": NaN,
      "AnaProgramAdı": "Fizyoterapi ve Rehabilitasyon",
      "DevletAynıSayı": 63,
      "DevletSıra": 12,
      "TÜMsıra": 35,
      "Doluluk Oranı": 100.0
    },
    {
      "Program Kodu": 105710024,
      "Üniversite Türü": "DEVLET",
      "Üniversite Adı": "İZMİR KATİP ÇELEBİ ÜNİVERSİTESİ",
      "Fakülte/Yüksekokul Adı": "Sağlık Bilimleri Fakültesi",
      "Program Adı": "Hemşirelik",
      "Puan Türü": "SAY",
      "Kontenjan": 160,
      "Yerleşen": 160,
      "En Küçük Puan": 37848043,
      "En Büyük Puan": 420.79259,
      "Değer": NaN,
      "AnaProgramAdı": "Hemşirelik",
      "DevletAynıSayı": 117,
      "DevletSıra": 33,
      "TÜMsıra": 57,
      "Doluluk Oranı": 100.0
    },
    {
      "Program Kodu": 105761091,
      "Üniversite Türü": "DEVLET",
      "Üniversite Adı": "İZMİR KATİP ÇELEBİ ÜNİVERSİTESİ",
      "Fakülte/Yüksekokul Adı": "Sağlık Bilimleri Fakültesi",
      "Program Adı": "Sosyal Hizmet",
      "Puan Türü": "EA",
      "Kontenjan": 30,
      "Yerleşen": 30,
      "En Küçük Puan": 31395044,
      "En Büyük Puan": 355.4953,
      "Değer": NaN,
      "AnaProgramAdı": "Sosyal Hizmet",
      "DevletAynıSayı": 61,
      "DevletSıra": 7,
      "TÜMsıra": 13,
      "Doluluk Oranı": 100.0
    },
    {
      "Program Kodu": 105761186,
      "Üniversite Türü": "DEVLET",
      "Üniversite Adı": "İZMİR KATİP ÇELEBİ ÜNİVERSİTESİ",
      "Fakülte/Yüksekokul Adı": "Sanat ve Tasarım Fakültesi",
      "Program Adı": "Görsel İletişim Tasarımı",
      "Puan Türü": "SÖZ",
      "Kontenjan": 35,
      "Yerleşen": 35,
      "En Küçük Puan": 34911828,
      "En Büyük Puan": 377.42155,
      "Değer": NaN,
      "AnaProgramAdı": "Görsel İletişim Tasarımı",
      "DevletAynıSayı": 22,
      "DevletSıra": 4,
      "TÜMsıra": 27,
      "Doluluk Oranı": 100.0
    },
    {
      "Program Kodu": 105761242,
      "Üniversite Türü": "DEVLET",
      "Üniversite Adı": "İZMİR KATİP ÇELEBİ ÜNİVERSİTESİ",
      "Fakülte/Yüksekokul Adı": "Sosyal ve Beşeri Bilimler Fakültesi",
      "Program Adı": "Bilgi Güvenliği Teknolojisi",
      "Puan Türü": "SAY",
      "Kontenjan": 30,
      "Yerleşen": 30,
      "En Küçük Puan": 34400529,
      "En Büyük Puan": 394.4415,
      "Değer": NaN,
      "AnaProgramAdı": "Bilgi Güvenliği Teknolojisi",
      "DevletAynıSayı": 6,
      "DevletSıra": 2,
      "TÜMsıra": 4,
      "Doluluk Oranı": 100.0
    },
    {
      "Program Kodu": 105761089,
      "Üniversite Türü": "DEVLET",
      "Üniversite Adı": "İZMİR KATİP ÇELEBİ ÜNİVERSİTESİ",
      "Fakülte/Yüksekokul Adı": "Sosyal ve Beşeri Bilimler Fakültesi",
      "Program Adı": "Bilgi ve Belge Yönetimi",
      "Puan Türü": "EA",
      "Kontenjan": 65,
      "Yerleşen": 66,
      "En Küçük Puan": 28134645,
      "En Büyük Puan": 328.9164,
      "Değer": NaN,
      "AnaProgramAdı": "Bilgi ve Belge Yönetimi",
      "DevletAynıSayı": 14,
      "DevletSıra": 7,
      "TÜMsıra": 8,
      "Doluluk Oranı": 101.53846153846153
    },
    {
      "Program Kodu": 105761031,
      "Üniversite Türü": "DEVLET",
      "Üniversite Adı": "İZMİR KATİP ÇELEBİ ÜNİVERSİTESİ",
      "Fakülte/Yüksekokul Adı": "Sosyal ve Beşeri Bilimler Fakültesi",
      "Program Adı": "Coğrafya",
      "Puan Türü": "SÖZ",
      "Kontenjan": 40,
      "Yerleşen": 41,
      "En Küçük Puan": 31655022,
      "En Büyük Puan": 339.66091,
      "Değer": NaN,
      "AnaProgramAdı": "Coğrafya",
      "DevletAynıSayı": 54,
      "DevletSıra": 11,
      "TÜMsıra": 11,
      "Doluluk Oranı": 102.49999999999999
    },
    {
      "Program Kodu": 105710209,
      "Üniversite Türü": "DEVLET",
      "Üniversite Adı": "İZMİR KATİP ÇELEBİ ÜNİVERSİTESİ",
      "Fakülte/Yüksekokul Adı": "Sosyal ve Beşeri Bilimler Fakültesi",
      "Program Adı": "Felsefe",
      "Puan Türü": "EA",
      "Kontenjan": 35,
      "Yerleşen": 36,
      "En Küçük Puan": 27263127,
      "En Büyük Puan": 337.51035,
      "Değer": NaN,
      "AnaProgramAdı": "Felsefe",
      "DevletAynıSayı": 66,
      "DevletSıra": 19,
      "TÜMsıra": 25,
      "Doluluk Oranı": 102.85714285714285
    },
    {
      "Program Kodu": 105761193,
      "Üniversite Türü": "DEVLET",
      "Üniversite Adı": "İZMİR KATİP ÇELEBİ ÜNİVERSİTESİ",
      "Fakülte/Yüksekokul Adı": "Sosyal ve Beşeri Bilimler Fakültesi",
      "Program Adı": "İngiliz Dili ve Edebiyatı (İngilizce)",
      "Puan Türü": "DİL",
      "Kontenjan": 40,
      "Yerleşen": 40,
      "En Küçük Puan": 41042437,
      "En Büyük Puan": 437.53873,
      "Değer": NaN,
      "AnaProgramAdı": "İngiliz Dili ve Edebiyatı",
      "DevletAynıSayı": 67,
      "DevletSıra": 12,
      "TÜMsıra": 27,
      "Doluluk Oranı": 100.0
    },
    {
      "Program Kodu": 105710193,
      "Üniversite Türü": "DEVLET",
      "Üniversite Adı": "İZMİR KATİP ÇELEBİ ÜNİVERSİTESİ",
      "Fakülte/Yüksekokul Adı": "Sosyal ve Beşeri Bilimler Fakültesi",
      "Program Adı": "Medya ve İletişim",
      "Puan Türü": "SÖZ",
      "Kontenjan": 80,
      "Yerleşen": 80,
      "En Küçük Puan": 32950444,
      "En Büyük Puan": 377.62958,
      "Değer": NaN,
      "AnaProgramAdı": "Medya ve İletişim",
      "DevletAynıSayı": 1,
      "DevletSıra": 1,
      "TÜMsıra": 3,
      "Doluluk Oranı": 100.0
    },
    {
      "Program Kodu": 105710299,
      "Üniversite Türü": "DEVLET",
      "Üniversite Adı": "İZMİR KATİP ÇELEBİ ÜNİVERSİTESİ",
      "Fakülte/Yüksekokul Adı": "Sosyal ve Beşeri Bilimler Fakültesi",
      "Program Adı": "Psikoloji",
      "Puan Türü": "EA",
      "Kontenjan": 50,
      "Yerleşen": 50,
      "En Küçük Puan": 38401093,
      "En Büyük Puan": 397.99119,
      "Değer": NaN,
      "AnaProgramAdı": "Psikoloji",
      "DevletAynıSayı": 79,
      "DevletSıra": 15,
      "TÜMsıra": 41,
      "Doluluk Oranı": 100.0
    },
    {
      "Program Kodu": 105710227,
      "Üniversite Türü": "DEVLET",
      "Üniversite Adı": "İZMİR KATİP ÇELEBİ ÜNİVERSİTESİ",
      "Fakülte/Yüksekokul Adı": "Sosyal ve Beşeri Bilimler Fakültesi",
      "Program Adı": "Sosyoloji",
      "Puan Türü": "EA",
      "Kontenjan": 30,
      "Yerleşen": 31,
      "En Küçük Puan": 30146489,
      "En Büyük Puan": 368.90392,
      "Değer": NaN,
      "AnaProgramAdı": "Sosyoloji",
      "DevletAynıSayı": 94,
      "DevletSıra": 18,
      "TÜMsıra": 40,
      "Doluluk Oranı": 103.33333333333334
    },
    {
      "Program Kodu": 105710218,
      "Üniversite Türü": "DEVLET",
      "Üniversite Adı": "İZMİR KATİP ÇELEBİ ÜNİVERSİTESİ",
      "Fakülte/Yüksekokul Adı": "Sosyal ve Beşeri Bilimler Fakültesi",
      "Program Adı": "Tarih",
      "Puan Türü": "SÖZ",
      "Kontenjan": 30,
      "Yerleşen": 31,
      "En Küçük Puan": 33053573,
      "En Büyük Puan": 402.2238,
      "Değer": NaN,
      "AnaProgramAdı": "Tarih",
      "DevletAynıSayı": 111,
      "DevletSıra": 21,
      "TÜMsıra": 35,
      "Doluluk Oranı": 103.33333333333334
    },
    {
      "Program Kodu": 105710263,
      "Üniversite Türü": "DEVLET",
      "Üniversite Adı": "İZMİR KATİP ÇELEBİ ÜNİVERSİTESİ",
      "Fakülte/Yüksekokul Adı": "Sosyal ve Beşeri Bilimler Fakültesi",
      "Program Adı": "Türk Dili ve Edebiyatı",
      "Puan Türü": "SÖZ",
      "Kontenjan": 30,
      "Yerleşen": 31,
      "En Küçük Puan": 32749519,
      "En Büyük Puan": 383.76914,
      "Değer": NaN,
      "AnaProgramAdı": "Türk Dili ve Edebiyatı",
      "DevletAynıSayı": 102,
      "DevletSıra": 20,
      "TÜMsıra": 35,
      "Doluluk Oranı": 103.33333333333334
    },
    {
      "Program Kodu": 105710272,
      "Üniversite Türü": "DEVLET",
      "Üniversite Adı": "İZMİR KATİP ÇELEBİ ÜNİVERSİTESİ",
      "Fakülte/Yüksekokul Adı": "Sosyal ve Beşeri Bilimler Fakültesi",
      "Program Adı": "Türk İslam Arkeolojisi",
      "Puan Türü": "EA",
      "Kontenjan": 30,
      "Yerleşen": 31,
      "En Küçük Puan": 2558594,
      "En Büyük Puan": 304.38979,
      "Değer": NaN,
      "AnaProgramAdı": "Türk İslam Arkeolojisi",
      "DevletAynıSayı": 1,
      "DevletSıra": 1,
      "TÜMsıra": 1,
      "Doluluk Oranı": 103.33333333333334
    },
    {
      "Program Kodu": 105710033,
      "Üniversite Türü": "DEVLET",
      "Üniversite Adı": "İZMİR KATİP ÇELEBİ ÜNİVERSİTESİ",
      "Fakülte/Yüksekokul Adı": "Su Ürünleri Fakültesi",
      "Program Adı": "Su Ürünleri Mühendisliği",
      "Puan Türü": "SAY",
      "Kontenjan": 35,
      "Yerleşen": 36,
      "En Küçük Puan": 26559035,
      "En Büyük Puan": 295.55328,
      "Değer": NaN,
      "AnaProgramAdı": "Su Ürünleri Mühendisliği",
      "DevletAynıSayı": 19,
      "DevletSıra": 4,
      "TÜMsıra": 4,
      "Doluluk Oranı": 102.85714285714285
    },
    {
      "Program Kodu": 105710015,
      "Üniversite Türü": "DEVLET",
      "Üniversite Adı": "İZMİR KATİP ÇELEBİ ÜNİVERSİTESİ",
      "Fakülte/Yüksekokul Adı": "Tıp Fakültesi",
      "Program Adı": "Tıp",
      "Puan Türü": "SAY",
      "Kontenjan": 215,
      "Yerleşen": 215,
      "En Küçük Puan": 4991976,
      "En Büyük Puan": 508.42523,
      "Değer": NaN,
      "AnaProgramAdı": "Tıp",
      "DevletAynıSayı": 119,
      "DevletSıra": 101,
      "TÜMsıra": 202,
      "Doluluk Oranı": 100.0
    },
    {
      "Program Kodu": 105710245,
      "Üniversite Türü": "DEVLET",
      "Üniversite Adı": "İZMİR KATİP ÇELEBİ ÜNİVERSİTESİ",
      "Fakülte/Yüksekokul Adı": "Tıp Fakültesi",
      "Program Adı": "Tıp (KKTC Uyruklu)",
      "Puan Türü": "SAY",
      "Kontenjan": 1,
      "Yerleşen": 0,
      "En Küçük Puan": 0,
      "En Büyük Puan": 0.0,
      "Değer": NaN,
      "AnaProgramAdı": "Tıp",
      "DevletAynıSayı": 119,
      "DevletSıra": 111,
      "TÜMsıra": 230,
      "Doluluk Oranı": 0.0
    },
    {
      "Program Kodu": 105761066,
      "Üniversite Türü": "DEVLET",
      "Üniversite Adı": "İZMİR KATİP ÇELEBİ ÜNİVERSİTESİ",
      "Fakülte/Yüksekokul Adı": "Turizm Fakültesi",
      "Program Adı": "Gastronomi ve Mutfak Sanatları",
      "Puan Türü": "SÖZ",
      "Kontenjan": 40,
      "Yerleşen": 40,
      "En Küçük Puan": 37174203,
      "En Büyük Puan": 396.11029,
      "Değer": NaN,
      "AnaProgramAdı": "Gastronomi ve Mutfak Sanatları",
      "DevletAynıSayı": 68,
      "DevletSıra": 8,
      "TÜMsıra": 31,
      "Doluluk Oranı": 100.0
    },
    {
      "Program Kodu": 105710139,
      "Üniversite Türü": "DEVLET",
      "Üniversite Adı": "İZMİR KATİP ÇELEBİ ÜNİVERSİTESİ",
      "Fakülte/Yüksekokul Adı": "Turizm Fakültesi",
      "Program Adı": "Turizm Rehberliği",
      "Puan Türü": "DİL",
      "Kontenjan": 65,
      "Yerleşen": 67,
      "En Küçük Puan": 38166922,
      "En Büyük Puan": 414.04526,
      "Değer": NaN,
      "AnaProgramAdı": "Turizm Rehberliği",
      "DevletAynıSayı": 38,
      "DevletSıra": 5,
      "TÜMsıra": 6,
      "Doluluk Oranı": 103.07692307692307
    },
    {
      "Program Kodu": 105761249,
      "Üniversite Türü": "DEVLET",
      "Üniversite Adı": "İZMİR KATİP ÇELEBİ ÜNİVERSİTESİ",
      "Fakülte/Yüksekokul Adı": "Turizm Fakültesi",
      "Program Adı": "Turizm ve Gastronomi Yönetimi Programları (İngilizce)",
      "Puan Türü": "EA",
      "Kontenjan": 30,
      "Yerleşen": 30,
      "En Küçük Puan": 30916219,
      "En Büyük Puan": 321.72267,
      "Değer": NaN,
      "AnaProgramAdı": "Turizm ve Gastronomi Yönetimi Programları",
      "DevletAynıSayı": 9,
      "DevletSıra": 5,
      "TÜMsıra": 5,
      "Doluluk Oranı": 100.0
    }
  ]
}